tradeoftimes-0.2.1.dist-info/METADATA
tradeoftimes-0.2.1.dist-info/RECORD
tradeoftimes-0.2.1.dist-info/WHEEL
tradeoftimes-0.2.1.dist-info/top_level.txt
tradet/__init__.py
tradet/__main__.py
tradet/game_diag.py
tradet/main_window.py
tradet/nick_diag.py
tradet/settings_diag.py
