Metadata-Version: 2.1
Name: tradeoftimes
Version: 0.2.1
Summary: Trade of Times: an experimental, demonstrative single & multiplayer RPG game, based on top of Peertable.
Home-page: UNKNOWN
Author: Gustavo6046
Author-email: gugurehermann@gmail.com
License: MIT
Keywords: p2p peer-to-peer peer network infrastructure game test experimental protocol demo rpg multiplayer
Platform: UNKNOWN
Requires-Dist: wxpython (>=4.0.3)
Requires-Dist: peertable (>=0.1.3.4)
Requires-Dist: ipgetter (>=0.7)
